odoo/addons/sale_coupon_promotion_generate_coupon/README.rst
odoo/addons/sale_coupon_promotion_generate_coupon/__init__.py
odoo/addons/sale_coupon_promotion_generate_coupon/__manifest__.py
odoo/addons/sale_coupon_promotion_generate_coupon/i18n/sale_coupon_promotion_generate_coupon.pot
odoo/addons/sale_coupon_promotion_generate_coupon/models/__init__.py
odoo/addons/sale_coupon_promotion_generate_coupon/models/coupon_program.py
odoo/addons/sale_coupon_promotion_generate_coupon/models/sale_order.py
odoo/addons/sale_coupon_promotion_generate_coupon/readme/CONTRIBUTORS.rst
odoo/addons/sale_coupon_promotion_generate_coupon/readme/DESCRIPTION.rst
odoo/addons/sale_coupon_promotion_generate_coupon/readme/USAGE.rst
odoo/addons/sale_coupon_promotion_generate_coupon/static/description/icon.png
odoo/addons/sale_coupon_promotion_generate_coupon/static/description/index.html
odoo/addons/sale_coupon_promotion_generate_coupon/tests/__init__.py
odoo/addons/sale_coupon_promotion_generate_coupon/tests/test_sale_coupon_promotion_generate_coupon.py
odoo/addons/sale_coupon_promotion_generate_coupon/views/coupon_program_views.xml
odoo13_addon_sale_coupon_promotion_generate_coupon-13.0.1.0.1.dev2.dist-info/METADATA
odoo13_addon_sale_coupon_promotion_generate_coupon-13.0.1.0.1.dev2.dist-info/WHEEL
odoo13_addon_sale_coupon_promotion_generate_coupon-13.0.1.0.1.dev2.dist-info/top_level.txt
odoo13_addon_sale_coupon_promotion_generate_coupon-13.0.1.0.1.dev2.dist-info/RECORD
